[
{"coverHeaders":{"Accept":"image/webp,*/*","Referer":"http://www.mm131.com","Connection":"keep-alive","User-Agent":"Mozilla/5.0 (Windows NT 10.0; Win64; x64; rv:65.0) Gecko/20100101 Firefox/65.0","Host":"img1.mm131.me","Accept-Encoding":"gzip, deflate","Accept-Language":"zh-CN,zh;q=0.8,zh-TW;q=0.7,zh-HK;q=0.5,en-US;q=0.3,en;q=0.2"},"list":{"action":{"key":{"keyCover":{"findAttrKey":"href","findType":"attribute","keyElement":{"findType":"tag","length":0,"list":false,"resultAttrKey":"src","resultType":"attr","start":0,"value":"img"},"length":0,"list":true,"start":0,"value":"http:\\/\\/www\\.mm131\\.com\\/\\w+\\/\\d+\\.html"},"keyLink":{"findAttrKey":"href","findType":"attribute","length":0,"list":true,"resultAttrKey":"href","resultType":"attr","start":0,"value":"http:\\/\\/www\\.mm131\\.com\\/\\w+\\/\\d+\\.html"},"keyName":{"findAttrKey":"href","findType":"attribute","length":0,"list":true,"resultType":"text","start":0,"value":"http:\\/\\/www\\.mm131\\.com\\/\\w+\\/\\d+\\.html"}},"length":0,"start":0},"url":"http://www.mm131.com/","version":0},"related":{"action":{"key":{"keyCover":{"findType":"id","keyElement":{"findType":"tag","length":0,"list":true,"resultAttrKey":"src","resultType":"attr","start":0,"value":"img"},"length":0,"list":false,"start":0,"value":"opic"},"keyLink":{"findType":"id","keyElement":{"findType":"tag","length":0,"list":true,"resultAttrKey":"href","resultType":"attr","start":0,"value":"a"},"length":0,"list":false,"start":0,"value":"opic"},"keyName":{"findType":"id","keyElement":{"findType":"tag","length":0,"list":true,"resultAttrKey":"alt","resultType":"attr","start":0,"value":"img"},"length":0,"list":false,"start":0,"value":"opic"}},"length":0,"start":0},"url":"http://www.mm131.com/xinggan/2478.html","version":0},"resource":{"action":{"key":{"keyCover":{"findType":"class","keyElement":{"findType":"tag","length":0,"list":false,"resultAttrKey":"src","resultType":"attr","start":0,"value":"img"},"length":0,"list":false,"start":0,"value":"content-pic"},"keyName":{"findType":"class","keyElement":{"findType":"tag","length":0,"list":false,"resultAttrKey":"alt","resultType":"attr","start":0,"value":"img"},"length":0,"list":false,"start":0,"value":"content-pic"}},"length":0,"start":0},"nextPageLink":{"findType":"text","length":0,"list":false,"resultAttrKey":"href","resultType":"attr","start":0,"value":"下一页"},"url":"http://www.mm131.com/xinggan/2478.html","version":0},"version":0},
{"coverHeaders":{"TE":"Trailers","Accept":"image/webp,*/*","Referer":"https://www.mzitu.com","Connection":"keep-alive","User-Agent":"Mozilla/5.0 (Windows NT 10.0; Win64; x64; rv:65.0) Gecko/20100101 Firefox/65.0","Host":"i.meizitu.net","Accept-Encoding":"gzip, deflate, br","Accept-Language":"zh-CN,zh;q=0.8,zh-TW;q=0.7,zh-HK;q=0.5,en-US;q=0.3,en;q=0.2"},"list":{"action":{"key":{"keyCover":{"findType":"class","keyElement":{"findAttrKey":"data-original","findType":"attribute","length":0,"list":true,"resultAttrKey":"data-original","resultType":"attr","start":0,"value":"https:\\/\\/i\\.meizitu\\.net\\/thumbs\\/.+\\.jpg"},"length":0,"list":false,"start":0,"value":"postlist"},"keyLink":{"findType":"class","keyElement":{"findType":"tag","keyElement":{"findType":"tag","length":0,"list":false,"resultAttrKey":"href","resultType":"attr","start":0,"value":"a"},"length":0,"list":true,"start":0,"value":"li"},"length":0,"list":false,"start":0,"value":"postlist"},"keyName":{"findType":"class","keyElement":{"findAttrKey":"data-original","findType":"attribute","length":0,"list":true,"resultAttrKey":"alt","resultType":"attr","start":0,"value":"https:\\/\\/i\\.meizitu\\.net\\/thumbs\\/.+\\.jpg"},"length":0,"list":false,"start":0,"value":"postlist"}},"length":0,"start":0},"url":"https://www.mzitu.com"},"resource":{"action":{"key":{"keyCover":{"findType":"class","keyElement":{"findType":"tag","length":0,"list":false,"resultAttrKey":"src","resultType":"attr","start":0,"value":"img"},"length":0,"list":false,"start":0,"value":"main-image"},"keyName":{"findType":"class","keyElement":{"findType":"tag","length":0,"list":false,"resultAttrKey":"alt","resultType":"attr","start":0,"value":"img"},"length":0,"list":false,"start":0,"value":"main-image"}},"length":0,"start":0},"nextPageLink":{"findType":"class","keyElement":{"findType":"text","length":0,"list":false,"relationship":{"index":0,"relation":"senior"},"resultAttrKey":"href","resultType":"attr","start":0,"value":"下一页"},"length":0,"list":false,"start":0,"value":"pagenavi"},"url":"https://www.mzitu.com/167298/44"}}
]